best_csv/__init__.py
best_csv/csv_to_dict.py
best_csv-1.2.dist-info/LICENSE
best_csv-1.2.dist-info/METADATA
best_csv-1.2.dist-info/WHEEL
best_csv-1.2.dist-info/top_level.txt
best_csv-1.2.dist-info/RECORD
