Metadata-Version: 2.1
Name: best_csv
Version: 1.2
Summary: Smarter Faster way from CSV to dict.
Author-email: Alexios Nersessian <nersessian@gmail.com>
Project-URL: Homepage, https://github.com/alekos3/best_csv.git
Classifier: Programming Language :: Python :: 3
Classifier: License :: OSI Approved :: MIT License
Classifier: Operating System :: OS Independent
Requires-Python: >=3.7
License-File: LICENSE
